{
    "slides": [
        {
            "src": "/images/messi.png",
            "alt": "image 1"
        },
        {
            "src": "/images/benzema.png",
            "alt": "image 2"
        },
        {
            "src": "/images/cristiano.png",
            "alt": "image 3"
        },
        {
            "src": "/images/diaz.png",
            "alt": "image 4"
        },
        {
            "src": "/images/Pedri.png",
            "alt": "image 5"
        },
        {
            "src": "/images/yamal.png",
            "alt": "image 6"
        },
        {
            "src": "/images/haaland.png",
            "alt": "image 7"
        },
        {
            "src": "/images/felix.png",
            "alt": "image 8"
        }
    ]
}